pypolyhedron/__init__.py
pypolyhedron/_cdd.cp37-win_amd64.pyd
pypolyhedron/example.py
pypolyhedron/hull3d.py
pypolyhedron/polyhedron.py
pypolyhedron-0.3.2.dist-info/METADATA
pypolyhedron-0.3.2.dist-info/WHEEL
pypolyhedron-0.3.2.dist-info/top_level.txt
pypolyhedron-0.3.2.dist-info/RECORD
